<recipe key="Kräuter - Senffilet">
   <keywords>
      <keyword/>
   </keywords>
   <ingredients>
      <ingredient>
         <num/>
         <unit/>
         <identifier>Schweinefilet</identifier>
      </ingredient>
      <ingredient>
         <num/>
         <unit/>
         <identifier>Salz</identifier>
      </ingredient>
      <ingredient>
         <num/>
         <unit/>
         <identifier>Pfeffer</identifier>
      </ingredient>
      <ingredient>
         <num>2</num>
         <unit>Eßl.</unit>
         <identifier>Öl </identifier>
      </ingredient>
      <ingredient>
         <num>150</num>
         <unit>g.</unit>
         <identifier>Schalotten</identifier>
      </ingredient>
      <ingredient>
         <num>1 - 2</num>
         <unit>Eßl.</unit>
         <identifier> Kräutersenf</identifier>
      </ingredient>
      <ingredient>
         <num>100</num>
         <unit>ccm</unit>
         <identifier>Brühe</identifier>
      </ingredient>
      <ingredient>
         <num>1</num>
         <unit>Becher</unit>
         <identifier>Kräuter-Creme fraiche</identifier>
      </ingredient>
      <ingredient>
         <num/>
         <unit/>
         <identifier>Zucker</identifier>
      </ingredient>
      <ingredient>
         <num/>
         <unit/>
         <identifier>Petersilie</identifier>
      </ingredient>
      <ingredient>
         <num/>
         <unit/>
         <identifier>Salz</identifier>
      </ingredient>
      <ingredient>
         <num/>
         <unit/>
         <identifier>Pfeffer</identifier>
      </ingredient>
      <ingredient>
         <num>einer</num>
         <unit>Prise</unit>
         <identifier> Zucker</identifier>
      </ingredient>
   </ingredients>
   <instructions>
Fleisch mit Salz und Pfeffer ein-
reiben und in heißem Öl braun
braten. Schalotten zufügen. Das
Fleisch mit Senf Bestreichen. Brühe
zufügen und in der geschlossenen
Pfanne 10 min schmoren. Fleisch
herausnehmen und warm halten.
Creme fraiche in die Soße rühren
und warm hal mit Salz, Pfeffer
und einerPrise Zucker abschmecken.
Gehackte Kräuter unterrühren.
</instructions>
</recipe>
